{
    "gameData": {
        "stat": {}
    },
    "textData": {
        "textInfo": [
            {
                "branch": [
                    1,
                    0,
                    0
                ],
                "charaterName": [
                    "python"
                ],
                "charaterSprite": [
                    "python_idle"
                ],
                "charaterText": "테스트 내용입니다 어느정도 길이가 있어야지 테스트가 가능하니 아무말이나 적어두겠습니다 감사합니다",
                "charaterVoice": "null",
                "BG": "기본배경_인게임",
                "charaterLocationType": 1,
                "selectType": 0
            },
            {
                "branch": [
                    1,
                    0,
                    1
                ],
                "charaterName": [
                    "python"
                ],
                "charaterSprite": [
                    "python_idle"
                ],
                "charaterText": "또 다른 테스트 내용입니다 전꺼와 같다면 테스트가 안됨으로 곂치지 않는 아무말이나 적어두겠습니다 감사합니다",
                "charaterVoice": "null",
                "BG": "기본배경_인게임",
                "charaterLocationType": 1,
                "selectType": 0
            },
            {
                "branch": [
                    1,
                    0,
                    2
                ],
                "charaterName": [
                    "python"
                ],
                "charaterSprite": [
                    "python_idle"
                ],
                "charaterText": "여기서부터는 모두 동일합니다 캐릭터 위치 여러명  등장등등 여러가지를 테스트합니다",
                "charaterVoice": "null",
                "BG": "기본배경_인게임",
                "charaterLocationType": 1,
                "selectType": 0
            },
            {
                "branch": [
                    1,
                    0,
                    3
                ],
                "charaterName": [
                    "python"
                ],
                "charaterSprite": [
                    "python_idle"
                ],
                "charaterText": "여기서부터는 모두 동일합니다 캐릭터 위치 여러명  등장등등 여러가지를 테스트합니다",
                "charaterVoice": "null",
                "BG": "기본배경_인게임",
                "charaterLocationType": 1,
                "selectType": 0
            },
            {
                "branch": [
                    1,
                    0,
                    4
                ],
                "charaterName": [
                    "python"
                ],
                "charaterSprite": [
                    "python_idle"
                ],
                "charaterText": "여기서부터는 모두 동일합니다 캐릭터 위치 여러명  등장등등 여러가지를 테스트합니다",
                "charaterVoice": "null",
                "BG": "기본배경_인게임",
                "charaterLocationType": 1,
                "selectType": 0
            },
            {
                "branch": [
                    1,
                    0,
                    5
                ],
                "charaterName": [
                    "python"
                ],
                "charaterSprite": [
                    "python_idle"
                ],
                "charaterText": "여기서부터는 모두 동일합니다 캐릭터 위치 여러명  등장등등 여러가지를 테스트합니다",
                "charaterVoice": "null",
                "BG": "기본배경_인게임",
                "charaterLocationType": 1,
                "selectType": 2
            },
            {
                "branch": [
                    1,
                    1,
                    0
                ],
                "charaterName": [
                    "python"
                ],
                "charaterSprite": [
                    "python_idle"
                ],
                "charaterText": "1번 테스트~~~~~",
                "charaterVoice": "null",
                "BG": "기본배경_인게임",
                "charaterLocationType": 1,
                "selectType": 0
            },
            {
                "branch": [
                    1,
                    1,
                    1
                ],
                "charaterName": [
                    "python"
                ],
                "charaterSprite": [
                    "python_idle"
                ],
                "charaterText": "1번테스트 2~~~~~~~~~",
                "charaterVoice": "null",
                "BG": "기본배경_인게임",
                "charaterLocationType": 1,
                "selectType": 0
            },
            {
                "branch": [
                    1,
                    2,
                    0
                ],
                "charaterName": [
                    "python"
                ],
                "charaterSprite": [
                    "python_idle"
                ],
                "charaterText": "2번 테스트~~~~~~~~~~~",
                "charaterVoice": "null",
                "BG": "기본배경_인게임",
                "charaterLocationType": 1,
                "selectType": 0
            },
            {
                "branch": [
                    1,
                    2,
                    1
                ],
                "charaterName": [
                    "python"
                ],
                "charaterSprite": [
                    "python_idle"
                ],
                "charaterText": "2번 테스트~~~~~~~~~~~~~~",
                "charaterVoice": "null",
                "BG": "기본배경_인게임",
                "charaterLocationType": 1,
                "selectType": 0
            },
            {
                "branch": [
                    2,
                    0,
                    0
                ],
                "charaterName": [
                    "c#"
                ],
                "charaterSprite": [
                    "c#_idle"
                ],
                "charaterText": "여기서부터는 모두 동일합니다 캐릭터 위치 여러명  등장등등 여러가지를 테스트합니다",
                "charaterVoice": "null",
                "BG": "기본배경_인게임",
                "charaterLocationType": 1,
                "selectType": 0
            },
            {
                "branch": [
                    2,
                    0,
                    1
                ],
                "charaterName": [
                    "c#"
                ],
                "charaterSprite": [
                    "c#_idle"
                ],
                "charaterText": "여기서부터는 모두 동일합니다 캐릭터 위치 여러명  등장등등 여러가지를 테스트합니다",
                "charaterVoice": "null",
                "BG": "기본배경_인게임",
                "charaterLocationType": 1,
                "selectType": 0
            },
            {
                "branch": [
                    2,
                    0,
                    2
                ],
                "charaterName": [
                    "c#"
                ],
                "charaterSprite": [
                    "c#_idle"
                ],
                "charaterText": "여기서부터는 모두 동일합니다 캐릭터 위치 여러명  등장등등 여러가지를 테스트합니다",
                "charaterVoice": "null",
                "BG": "기본배경_인게임",
                "charaterLocationType": 1,
                "selectType": 0
            },
            {
                "branch": [
                    2,
                    0,
                    3
                ],
                "charaterName": [
                    "c#"
                ],
                "charaterSprite": [
                    "c#_idle"
                ],
                "charaterText": "여기서부터는 모두 동일합니다 캐릭터 위치 여러명  등장등등 여러가지를 테스트합니다",
                "charaterVoice": "null",
                "BG": "기본배경_인게임",
                "charaterLocationType": 1,
                "selectType": 0
            },
            {
                "branch": [
                    2,
                    0,
                    4
                ],
                "charaterName": [
                    "c#"
                ],
                "charaterSprite": [
                    "c#_idle"
                ],
                "charaterText": "여기서부터는 모두 동일합니다 캐릭터 위치 여러명  등장등등 여러가지를 테스트합니다",
                "charaterVoice": "null",
                "BG": "기본배경_인게임",
                "charaterLocationType": 1,
                "selectType": 0
            },
            {
                "branch": [
                    2,
                    0,
                    5
                ],
                "charaterName": [
                    "c#"
                ],
                "charaterSprite": [
                    "c#_idle"
                ],
                "charaterText": "여기서부터는 모두 동일합니다 캐릭터 위치 여러명  등장등등 여러가지를 테스트합니다",
                "charaterVoice": "null",
                "BG": "기본배경_인게임",
                "charaterLocationType": 1,
                "selectType": 0
            },
            {
                "branch": [
                    2,
                    0,
                    6
                ],
                "charaterName": [
                    "c#"
                ],
                "charaterSprite": [
                    "c#_idle"
                ],
                "charaterText": "여기서부터는 모두 동일합니다 캐릭터 위치 여러명  등장등등 여러가지를 테스트합니다",
                "charaterVoice": "null",
                "BG": "기본배경_인게임",
                "charaterLocationType": 1,
                "selectType": 0
            },
            {
                "branch": [
                    2,
                    0,
                    7
                ],
                "charaterName": [
                    "c#"
                ],
                "charaterSprite": [
                    "c#_idle"
                ],
                "charaterText": "여기서부터는 모두 동일합니다 캐릭터 위치 여러명  등장등등 여러가지를 테스트합니다",
                "charaterVoice": "null",
                "BG": "기본배경_인게임",
                "charaterLocationType": 1,
                "selectType": 0
            },
            {
                "branch": [
                    2,
                    0,
                    8
                ],
                "charaterName": [
                    "c#"
                ],
                "charaterSprite": [
                    "c#_idle"
                ],
                "charaterText": "여기서부터는 모두 동일합니다 캐릭터 위치 여러명  등장등등 여러가지를 테스트합니다",
                "charaterVoice": "null",
                "BG": "기본배경_인게임",
                "charaterLocationType": 1,
                "selectType": 0
            },
            {
                "branch": [
                    2,
                    0,
                    9
                ],
                "charaterName": [
                    "c#"
                ],
                "charaterSprite": [
                    "c#_idle"
                ],
                "charaterText": "여기서부터는 모두 동일합니다 캐릭터 위치 여러명  등장등등 여러가지를 테스트합니다",
                "charaterVoice": "null",
                "BG": "기본배경_인게임",
                "charaterLocationType": 1,
                "selectType": 0
            },
            {
                "branch": [
                    3,
                    0,
                    0
                ],
                "charaterName": [
                    "c++"
                ],
                "charaterSprite": [
                    "c++_idle"
                ],
                "charaterText": "여기서부터는 모두 동일합니다 캐릭터 위치 여러명  등장등등 여러가지를 테스트합니다",
                "charaterVoice": "null",
                "BG": "기본배경_인게임",
                "charaterLocationType": 1,
                "selectType": 0
            },
            {
                "branch": [
                    4,
                    0,
                    0
                ],
                "charaterName": [
                    "c"
                ],
                "charaterSprite": [
                    "c_idle"
                ],
                "charaterText": "여기서부터는 모두 동일합니다 캐릭터 위치 여러명  등장등등 여러가지를 테스트합니다",
                "charaterVoice": "null",
                "BG": "기본배경_인게임",
                "charaterLocationType": 1,
                "selectType": 0
            },
            {
                "branch": [
                    5,
                    0,
                    0
                ],
                "charaterName": [
                    "html"
                ],
                "charaterSprite": [
                    "html_idle"
                ],
                "charaterText": "여기서부터는 모두 동일합니다 캐릭터 위치 여러명  등장등등 여러가지를 테스트합니다",
                "charaterVoice": "null",
                "BG": "기본배경_인게임",
                "charaterLocationType": 1,
                "selectType": 0
            },
            {
                "branch": [
                    6,
                    0,
                    0
                ],
                "charaterName": [
                    "java"
                ],
                "charaterSprite": [
                    "java_idle"
                ],
                "charaterText": "여기서부터는 모두 동일합니다 캐릭터 위치 여러명  등장등등 여러가지를 테스트합니다",
                "charaterVoice": "null",
                "BG": "기본배경_인게임",
                "charaterLocationType": 1,
                "selectType": 0
            },
            {
                "branch": [
                    7,
                    0,
                    0
                ],
                "charaterName": [
                    "java"
                ],
                "charaterSprite": [
                    "java_idle"
                ],
                "charaterText": "여기서부터는 모두 동일합니다 캐릭터 위치 여러명  등장등등 여러가지를 테스트합니다",
                "charaterVoice": "null",
                "BG": "기본배경_인게임",
                "charaterLocationType": 1,
                "selectType": 0
            }
        ]
    },
    "spriteData": {},
    "storyData": {
        "storyInfo": [
            {
                "number": 1,
                "image": "python",
                "title": "구름다리 위에서",
                "content": "내용1",
                "condition1": [],
                "condition2": [],
                "condition3": []
            },
            {
                "number": 2,
                "image": "c#",
                "title": "동아리 박람회",
                "content": "내용2",
                "condition1": [],
                "condition2": [],
                "condition3": []
            },
            {
                "number": 3,
                "image": "c++",
                "title": "ExP 면접",
                "content": "내용3",
                "condition1": [],
                "condition2": [],
                "condition3": []
            },
            {
                "number": 4,
                "image": "c",
                "title": "동방에서 일어난 일",
                "content": "내용4",
                "condition1": [],
                "condition2": [],
                "condition3": []
            },
            {
                "number": 5,
                "image": "html",
                "title": "홍대 길거리에서",
                "content": "내용5",
                "condition1": [],
                "condition2": [],
                "condition3": []
            },
            {
                "number": 6,
                "image": "java",
                "title": "T동 속 화초",
                "content": "내용6",
                "condition1": [],
                "condition2": [],
                "condition3": []
            },
            {
                "number": 7,
                "image": "java",
                "title": "테스트2",
                "content": "내용7",
                "condition1": [
                    6
                ],
                "condition2": [],
                "condition3": []
            }
        ]
    },
    "selectData": {
        "selectInfo": [
            {
                "selectType": 0,
                "selectText": [],
                "branchChange": []
            },
            {
                "selectType": 1,
                "selectText": [],
                "branchChange": []
            },
            {
                "selectType": 2,
                "selectText": [
                    "1번 선택을 한다",
                    "2번 선택을 한다"
                ],
                "branchChange": [
                    1,
                    2
                ]
            },
            {
                "selectType": 3,
                "selectText": [
                    "3번 선택을 한다",
                    "4번 선택을 한다"
                ],
                "branchChange": [
                    1,
                    2
                ]
            },
            {
                "selectType": 4,
                "selectText": [
                    "1번 선택을 한다",
                    "2번 선택을 한다"
                ],
                "branchChange": [
                    1,
                    2
                ]
            },
            {
                "selectType": 5,
                "selectText": [
                    "1번 선택을 한다",
                    "2번 선택을 한다"
                ],
                "branchChange": [
                    1,
                    2
                ]
            },
            {
                "selectType": 6,
                "selectText": [
                    "1번 선택을 한다",
                    "2번 선택을 한다"
                ],
                "branchChange": [
                    1,
                    2
                ]
            }
        ]
    },
    "inGameData": {
        "loadingCnt": 4,
        "maxCnt": 4,
        "number": 0
    }
}